{
  "$schema": "../manifold-structure.schema.json",
  "schema_version": 3,
  "feature": "[CUSTOMIZE: your-api-name]-api",
  "phase": "INITIALIZED",
  "template": "api",
  "template_version": 1,
  "constraints": {
    "business": [
      { "id": "B1", "type": "invariant" },
      { "id": "B2", "type": "boundary" },
      { "id": "B3", "type": "goal" }
    ],
    "technical": [
      { "id": "T1", "type": "boundary" },
      { "id": "T2", "type": "boundary" },
      { "id": "T3", "type": "invariant" },
      { "id": "T4", "type": "goal" },
      { "id": "T5", "type": "boundary" }
    ],
    "user_experience": [
      { "id": "U1", "type": "boundary" },
      { "id": "U2", "type": "goal" },
      { "id": "U3", "type": "boundary" }
    ],
    "security": [
      { "id": "S1", "type": "invariant" },
      { "id": "S2", "type": "invariant" },
      { "id": "S3", "type": "boundary" },
      { "id": "S4", "type": "goal" }
    ],
    "operational": [
      { "id": "O1", "type": "boundary" },
      { "id": "O2", "type": "goal" },
      { "id": "O3", "type": "boundary" }
    ]
  },
  "tensions": [
    { "id": "TN1", "type": "trade_off", "between": ["T1", "O2"], "status": "resolved" },
    { "id": "TN2", "type": "trade_off", "between": ["B1", "T3"], "status": "resolved" },
    { "id": "TN3", "type": "trade_off", "between": ["S2", "U3"], "status": "resolved" },
    { "id": "TN4", "type": "hidden_dependency", "between": ["S1", "O1"], "status": "resolved" }
  ],
  "anchors": {
    "required_truths": [
      { "id": "RT-1", "status": "NOT_SATISFIED", "maps_to": ["S1", "S2"] },
      { "id": "RT-2", "status": "NOT_SATISFIED", "maps_to": ["T3", "T5"] },
      { "id": "RT-3", "status": "NOT_SATISFIED", "maps_to": ["B2", "T1", "T2"] },
      { "id": "RT-4", "status": "NOT_SATISFIED", "maps_to": ["O1", "O2"] }
    ]
  },
  "iterations": [],
  "convergence": { "status": "NOT_STARTED" }
}
